setup.py
deserializer/__init__.py
deserializer/mixins.py
django_deserializer.egg-info/PKG-INFO
django_deserializer.egg-info/SOURCES.txt
django_deserializer.egg-info/dependency_links.txt
django_deserializer.egg-info/not-zip-safe
django_deserializer.egg-info/requires.txt
django_deserializer.egg-info/top_level.txt