Metadata-Version: 1.0
Name: django-deserializer
Version: 0.11
Summary: A Django Mixin capable of deserializing a request's body into python data structures.
Home-page: https://github.com/stargazer/django-deserializer/
Author: C. Paschalides
Author-email: already.late@gmail.com
License: WTFPL
Platform: UNKNOWN
Classifier: Programming Language :: Python
Classifier: Operating System :: OS Independent
Classifier: Topic :: Internet :: WWW/HTTP
Classifier: Framework :: Django
Classifier: Intended Audience :: Developers
Classifier: License :: Freely Distributable
